display/DE1_SoC_CAMERA_WORKING_RST_NEW_IMG/v/image_resize_avg_simple.sv
module image_resize_avg_simple (
    input  wire        clk,        // Clock
    input  wire        rst_n,       // Active-low reset
    input  wire        KEY_2,           // Active-low key to start
    input  wire [7:0]  Read_DATA2,      // 8-bit pixel from SDRAM
    output reg         start_resize,    // Trigger SDRAM read
    output reg  [22:0] read_addr_resize // SDRAM read address
);

    // Output array: 32x32, 8-bit pixels
    reg [7:0] out [0:31][0:31];

    // Internal registers
    reg [31:0] pixel_sum;         // Accumulator for 20x15 block
    reg [4:0]  pixel_x;           // Pixel x in block (0 to 19)
    reg [3:0]  pixel_y;           // Pixel y in block (0 to 14)
    reg [5:0]  block_x, block_y;  // Block indices (0 to 31)
    reg        running;           // Process active flag
    reg        triggered;         // Tracks if KEY_2 has triggered

    // Main logic
    always_ff @(posedge clk or negedge rst_n) begin
        if (!rst_n) begin
            start_resize <= 1'b0;
            read_addr_resize <= 23'd0;
            pixel_sum <= 32'd0;
            pixel_x <= 5'd0;
            pixel_y <= 4'd0;
            block_x <= 6'd0;
            block_y <= 6'd0;
            running <= 1'b0;
            triggered <= 1'b0; // Reset allows new trigger
            // Clear output array
            for (int i = 0; i < 32; i++) begin
                for (int j = 0; j < 32; j++) begin
                    out[i][j] <= 8'd0;
                end
            end
        end else begin
            if (!KEY_2 && !triggered && !running) begin
                // Start process only if not triggered before
                start_resize <= 1'b1;
                read_addr_resize <= 23'd0;
                pixel_sum <= 32'd0;
                pixel_x <= 5'd0;
                pixel_y <= 4'd0;
                block_x <= 6'd0;
                block_y <= 6'd0;
                running <= 1'b1;
                triggered <= 1'b1; // Prevent further triggers
            end else if (running) begin
                start_resize <= 1'b0; // Deassert after read
                pixel_sum <= pixel_sum + Read_DATA2; // Accumulate pixel
                if (pixel_x == 19 && pixel_y == 14) begin
                    // End of 20x15 block: compute and store average
                    out[block_y][block_x] <= pixel_sum / 300;
                    pixel_sum <= 32'd0;
                    pixel_x <= 5'd0;
                    pixel_y <= 4'd0;
                    if (block_x == 31 && block_y == 31) begin
                        // Done with all blocks
                        running <= 1'b0;
                    end else if (block_x == 31) begin
                        // Next row of blocks
                        block_x <= 6'd0;
                        block_y <= block_y + 1;
                        read_addr_resize <= (block_y + 1) * 15 * 640;
                    end else begin
                        // Next block in row
                        block_x <= block_x + 1;
                        read_addr_resize <= block_y * 15 * 640 + (block_x + 1) * 20;
                    end
                end else begin
                    // Next pixel in block
                    if (pixel_x == 19) begin
                        pixel_x <= 5'd0;
                        pixel_y <= pixel_y + 1;
                    end else begin
                        pixel_x <= pixel_x + 1;
                    end
                    read_addr_resize <= read_addr_resize + 1;
                    start_resize <= 1'b1; // Trigger next read
                end
            end
        end
    end

endmodule

display/DE1_SoC_CAMERA_WORKING_RST_NEW_IMG/v/image_resize_avg_simple_tb_simple.v
`timescale 1ns/1ps

module tb_image_resize_avg_simple;

  // Inputs to DUT
  reg         clk;
  reg         rst_n;
  reg         KEY_2;
  reg  [7:0]  Read_DATA2;

  // Outputs from DUT
  wire        start_resize;
  wire [22:0] read_addr_resize;

  // Instantiate the DUT
  image_resize_avg_simple dut (
    .clk               (clk),
    .rst_n             (rst_n),
    .KEY_2             (KEY_2),
    .Read_DATA2        (Read_DATA2),
    .start_resize      (start_resize),
    .read_addr_resize  (read_addr_resize)
  );

  // 1) Clock gen: 50 MHz → 20 ns period
  initial clk = 0;
  always #10 clk = ~clk;

  // 2) Data source: hold 600 after reset
  always @(posedge clk) begin
    if (!rst_n)
      Read_DATA2 <= 8'd0;
    else
      Read_DATA2 <= 8'd600;
  end

  // 3) Stimulus: reset, pulse KEY_2, run…
  initial begin
    $dumpfile("tb_image_resize_avg_simple.vcd");
    $dumpvars(0, tb_image_resize_avg_simple);

    rst_n = 1'b0;
    KEY_2 = 1'b1;
    #100;

    rst_n = 1'b1;
    #50;

    KEY_2 = 1'b0;  // start
    #20;
    KEY_2 = 1'b1;

    #50000;       // enough time for 3 blocks
    $finish;
  end

  // optional monitor
  initial begin
   // $monitor("%0t | bx=%0d by=%0d px=%0d py=%0d out00=%0d",
          //   $time, dut.block_x, dut.block_y, dut.pixel_x, dut.pixel_y, dut.out[0][0]);
  end

  // 4) Compute expected averages (all 600)
  reg [7:0] expected0, expected1, expected2;
  initial begin
    expected0 = 8'd600;
    expected1 = 8'd600;
    expected2 = 8'd600;
    $display("Expecting out[0][0]=%0d, out[0][1]=%0d, out[0][2]=%0d",
             expected0, expected1, expected2);
  end

  // 5a) Check block [0][0] when block_x rolls to 1
  always @(posedge clk) begin
    if (dut.block_x == 1 && dut.block_y == 0 &&
        dut.pixel_x == 0 && dut.pixel_y == 0) begin
      if (dut.out[0][0] !== expected0)
        $display("FAIL block[0][0]=%0d, expected=%0d",
               dut.out[0][0], expected0);
      else
        $display("PASS block[0][0]=%0d", expected0);
    end
  end

  // 5b) Check block [0][1] when block_x rolls to 2
  always @(posedge clk) begin
    if (dut.block_x == 2 && dut.block_y == 0 &&
        dut.pixel_x == 0 && dut.pixel_y == 0) begin
      if (dut.out[0][1] !== expected1)
        $display("FAIL block[0][1]=%0d, expected=%0d",
               dut.out[0][1], expected1);
      else
        $display("PASS block[0][1]=%0d", expected1);
    end
  end

  // 5c) Check block [0][2] when block_x rolls to 3, then finish
  always @(posedge clk) begin
    if (dut.block_x == 3 && dut.block_y == 0 &&
        dut.pixel_x == 0 && dut.pixel_y == 0) begin
      if (dut.out[0][2] !== expected2)
        $display("FAIL block[0][2]=%0d, expected=%0d",
               dut.out[0][2], expected2);
      else
        $display("PASS block[0][2]=%0d", expected2);

      #10 $finish;
    end
  end

endmodule

display/DE1_SoC_CAMERA_WORKING_RST_NEW_IMG/v/tb_image_resize_avg_simple.vcd
$date
	Fri Apr 25 17:44:56 2025
$end
$version
	ModelSim Version 10.5b
$end
$timescale
	1ps
$end

$scope module tb_image_resize_avg_simple $end
$var reg 1 ! clk $end
$var reg 1 " rst_n $end
$var reg 1 # KEY_2 $end
$var reg 8 $ Read_DATA2 [7:0] $end
$var wire 1 % start_resize $end
$var wire 1 & read_addr_resize [22] $end
$var wire 1 ' read_addr_resize [21] $end
$var wire 1 ( read_addr_resize [20] $end
$var wire 1 ) read_addr_resize [19] $end
$var wire 1 * read_addr_resize [18] $end
$var wire 1 + read_addr_resize [17] $end
$var wire 1 , read_addr_resize [16] $end
$var wire 1 - read_addr_resize [15] $end
$var wire 1 . read_addr_resize [14] $end
$var wire 1 / read_addr_resize [13] $end
$var wire 1 0 read_addr_resize [12] $end
$var wire 1 1 read_addr_resize [11] $end
$var wire 1 2 read_addr_resize [10] $end
$var wire 1 3 read_addr_resize [9] $end
$var wire 1 4 read_addr_resize [8] $end
$var wire 1 5 read_addr_resize [7] $end
$var wire 1 6 read_addr_resize [6] $end
$var wire 1 7 read_addr_resize [5] $end
$var wire 1 8 read_addr_resize [4] $end
$var wire 1 9 read_addr_resize [3] $end
$var wire 1 : read_addr_resize [2] $end
$var wire 1 ; read_addr_resize [1] $end
$var wire 1 < read_addr_resize [0] $end
$var reg 8 = expected0 [7:0] $end
$var reg 8 > expected1 [7:0] $end
$var reg 8 ? expected2 [7:0] $end

$scope module dut $end
$var wire 1 @ clk $end
$var wire 1 A rst_n $end
$var wire 1 B KEY_2 $end
$var wire 1 C Read_DATA2 [7] $end
$var wire 1 D Read_DATA2 [6] $end
$var wire 1 E Read_DATA2 [5] $end
$var wire 1 F Read_DATA2 [4] $end
$var wire 1 G Read_DATA2 [3] $end
$var wire 1 H Read_DATA2 [2] $end
$var wire 1 I Read_DATA2 [1] $end
$var wire 1 J Read_DATA2 [0] $end
$var reg 1 K start_resize $end
$var reg 23 L read_addr_resize [22:0] $end
$var reg 32 M pixel_sum [31:0] $end
$var reg 5 N pixel_x [4:0] $end
$var reg 4 O pixel_y [3:0] $end
$var reg 6 P block_x [5:0] $end
$var reg 6 Q block_y [5:0] $end
$var reg 1 R running $end
$var reg 1 S triggered $end
$upscope $end
$upscope $end
$enddefinitions $end
#0
$dumpvars
0!
0"
1#
bx $
0K
b0 L
b0 M
b0 N
b0 O
b0 P
b0 Q
0R
0S
b1011000 =
b1011000 >
b1011000 ?
0%
0<
0;
0:
09
08
07
06
05
04
03
02
01
00
0/
0.
0-
0,
0+
0*
0)
0(
0'
0&
xJ
xI
xH
xG
xF
xE
xD
xC
1B
0A
0@
$end
#10000
1!
1@
b0 $
0J
0I
0H
0G
0F
0E
0D
0C
#20000
0!
0@
#30000
1!
1@
#40000
0!
0@
#50000
1!
1@
#60000
0!
0@
#70000
1!
1@
#80000
0!
0@
#90000
1!
1@
#100000
1"
0!
1A
0@
#110000
1!
1@
b1011000 $
1G
1F
1D
#120000
0!
0@
#130000
1!
1@
#140000
0!
0@
#150000
0#
1!
0B
1@
1K
1R
1S
1%
#160000
0!
0@
#170000
1#
1!
1B
1@
0K
b1011000 M
b1 N
b1 L
1K
1<
#180000
0!
0@
#190000
1!
1@
0K
b10110000 M
b10 N
b10 L
1K
0<
1;
#200000
0!
0@
#210000
1!
1@
0K
b100001000 M
b11 N
b11 L
1K
1<
#220000
0!
0@
#230000
1!
1@
0K
b101100000 M
b100 N
b100 L
1K
0<
0;
1:
#240000
0!
0@
#250000
1!
1@
0K
b110111000 M
b101 N
b101 L
1K
1<
#260000
0!
0@
#270000
1!
1@
0K
b1000010000 M
b110 N
b110 L
1K
0<
1;
#280000
0!
0@
#290000
1!
1@
0K
b1001101000 M
b111 N
b111 L
1K
1<
#300000
0!
0@
#310000
1!
1@
0K
b1011000000 M
b1000 N
b1000 L
1K
0<
0;
0:
19
#320000
0!
0@
#330000
1!
1@
0K
b1100011000 M
b1001 N
b1001 L
1K
1<
#340000
0!
0@
#350000
1!
1@
0K
b1101110000 M
b1010 N
b1010 L
1K
0<
1;
#360000
0!
0@
#370000
1!
1@
0K
b1111001000 M
b1011 N
b1011 L
1K
1<
#380000
0!
0@
#390000
1!
1@
0K
b10000100000 M
b1100 N
b1100 L
1K
0<
0;
1:
#400000
0!
0@
#410000
1!
1@
0K
b10001111000 M
b1101 N
b1101 L
1K
1<
#420000
0!
0@
#430000
1!
1@
0K
b10011010000 M
b1110 N
b1110 L
1K
0<
1;
#440000
0!
0@
#450000
1!
1@
0K
b10100101000 M
b1111 N
b1111 L
1K
1<
#460000
0!
0@
#470000
1!
1@
0K
b10110000000 M
b10000 N
b10000 L
1K
0<
0;
0:
09
18
#480000
0!
0@
#490000
1!
1@
0K
b10111011000 M
b10001 N
b10001 L
1K
1<
#500000
0!
0@
#510000
1!
1@
0K
b11000110000 M
b10010 N
b10010 L
1K
0<
1;
#520000
0!
0@
#530000
1!
1@
0K
b11010001000 M
b10011 N
b10011 L
1K
1<
#540000
0!
0@
#550000
1!
1@
0K
b11011100000 M
b0 N
b1 O
b10100 L
1K
0<
0;
1:
#560000
0!
0@
#570000
1!
1@
0K
b11100111000 M
b1 N
b10101 L
1K
1<
#580000
0!
0@
#590000
1!
1@
0K
b11110010000 M
b10 N
b10110 L
1K
0<
1;
#600000
0!
0@
#610000
1!
1@
0K
b11111101000 M
b11 N
b10111 L
1K
1<
#620000
0!
0@
#630000
1!
1@
0K
b100001000000 M
b100 N
b11000 L
1K
0<
0;
0:
19
#640000
0!
0@
#650000
1!
1@
0K
b100010011000 M
b101 N
b11001 L
1K
1<
#660000
0!
0@
#670000
1!
1@
0K
b100011110000 M
b110 N
b11010 L
1K
0<
1;
#680000
0!
0@
#690000
1!
1@
0K
b100101001000 M
b111 N
b11011 L
1K
1<
#700000
0!
0@
#710000
1!
1@
0K
b100110100000 M
b1000 N
b11100 L
1K
0<
0;
1:
#720000
0!
0@
#730000
1!
1@
0K
b100111111000 M
b1001 N
b11101 L
1K
1<
#740000
0!
0@
#750000
1!
1@
0K
b101001010000 M
b1010 N
b11110 L
1K
0<
1;
#760000
0!
0@
#770000
1!
1@
0K
b101010101000 M
b1011 N
b11111 L
1K
1<
#780000
0!
0@
#790000
1!
1@
0K
b101100000000 M
b1100 N
b100000 L
1K
0<
0;
0:
09
08
17
#800000
0!
0@
#810000
1!
1@
0K
b101101011000 M
b1101 N
b100001 L
1K
1<
#820000
0!
0@
#830000
1!
1@
0K
b101110110000 M
b1110 N
b100010 L
1K
0<
1;
#840000
0!
0@
#850000
1!
1@
0K
b110000001000 M
b1111 N
b100011 L
1K
1<
#860000
0!
0@
#870000
1!
1@
0K
b110001100000 M
b10000 N
b100100 L
1K
0<
0;
1:
#880000
0!
0@
#890000
1!
1@
0K
b110010111000 M
b10001 N
b100101 L
1K
1<
#900000
0!
0@
#910000
1!
1@
0K
b110100010000 M
b10010 N
b100110 L
1K
0<
1;
#920000
0!
0@
#930000
1!
1@
0K
b110101101000 M
b10011 N
b100111 L
1K
1<
#940000
0!
0@
#950000
1!
1@
0K
b110111000000 M
b0 N
b10 O
b101000 L
1K
0<
0;
0:
19
#960000
0!
0@
#970000
1!
1@
0K
b111000011000 M
b1 N
b101001 L
1K
1<
#980000
0!
0@
#990000
1!
1@
0K
b111001110000 M
b10 N
b101010 L
1K
0<
1;
#1000000
0!
0@
#1010000
1!
1@
0K
b111011001000 M
b11 N
b101011 L
1K
1<
#1020000
0!
0@
#1030000
1!
1@
0K
b111100100000 M
b100 N
b101100 L
1K
0<
0;
1:
#1040000
0!
0@
#1050000
1!
1@
0K
b111101111000 M
b101 N
b101101 L
1K
1<
#1060000
0!
0@
#1070000
1!
1@
0K
b111111010000 M
b110 N
b101110 L
1K
0<
1;
#1080000
0!
0@
#1090000
1!
1@
0K
b1000000101000 M
b111 N
b101111 L
1K
1<
#1100000
0!
0@
#1110000
1!
1@
0K
b1000010000000 M
b1000 N
b110000 L
1K
0<
0;
0:
09
18
#1120000
0!
0@
#1130000
1!
1@
0K
b1000011011000 M
b1001 N
b110001 L
1K
1<
#1140000
0!
0@
#1150000
1!
1@
0K
b1000100110000 M
b1010 N
b110010 L
1K
0<
1;
#1160000
0!
0@
#1170000
1!
1@
0K
b1000110001000 M
b1011 N
b110011 L
1K
1<
#1180000
0!
0@
#1190000
1!
1@
0K
b1000111100000 M
b1100 N
b110100 L
1K
0<
0;
1:
#1200000
0!
0@
#1210000
1!
1@
0K
b1001000111000 M
b1101 N
b110101 L
1K
1<
#1220000
0!
0@
#1230000
1!
1@
0K
b1001010010000 M
b1110 N
b110110 L
1K
0<
1;
#1240000
0!
0@
#1250000
1!
1@
0K
b1001011101000 M
b1111 N
b110111 L
1K
1<
#1260000
0!
0@
#1270000
1!
1@
0K
b1001101000000 M
b10000 N
b111000 L
1K
0<
0;
0:
19
#1280000
0!
0@
#1290000
1!
1@
0K
b1001110011000 M
b10001 N
b111001 L
1K
1<
#1300000
0!
0@
#1310000
1!
1@
0K
b1001111110000 M
b10010 N
b111010 L
1K
0<
1;
#1320000
0!
0@
#1330000
1!
1@
0K
b1010001001000 M
b10011 N
b111011 L
1K
1<
#1340000
0!
0@
#1350000
1!
1@
0K
b1010010100000 M
b0 N
b11 O
b111100 L
1K
0<
0;
1:
#1360000
0!
0@
#1370000
1!
1@
0K
b1010011111000 M
b1 N
b111101 L
1K
1<
#1380000
0!
0@
#1390000
1!
1@
0K
b1010101010000 M
b10 N
b111110 L
1K
0<
1;
#1400000
0!
0@
#1410000
1!
1@
0K
b1010110101000 M
b11 N
b111111 L
1K
1<
#1420000
0!
0@
#1430000
1!
1@
0K
b1011000000000 M
b100 N
b1000000 L
1K
0<
0;
0:
09
08
07
16
#1440000
0!
0@
#1450000
1!
1@
0K
b1011001011000 M
b101 N
b1000001 L
1K
1<
#1460000
0!
0@
#1470000
1!
1@
0K
b1011010110000 M
b110 N
b1000010 L
1K
0<
1;
#1480000
0!
0@
#1490000
1!
1@
0K
b1011100001000 M
b111 N
b1000011 L
1K
1<
#1500000
0!
0@
#1510000
1!
1@
0K
b1011101100000 M
b1000 N
b1000100 L
1K
0<
0;
1:
#1520000
0!
0@
#1530000
1!
1@
0K
b1011110111000 M
b1001 N
b1000101 L
1K
1<
#1540000
0!
0@
#1550000
1!
1@
0K
b1100000010000 M
b1010 N
b1000110 L
1K
0<
1;
#1560000
0!
0@
#1570000
1!
1@
0K
b1100001101000 M
b1011 N
b1000111 L
1K
1<
#1580000
0!
0@
#1590000
1!
1@
0K
b1100011000000 M
b1100 N
b1001000 L
1K
0<
0;
0:
19
#1600000
0!
0@
#1610000
1!
1@
0K
b1100100011000 M
b1101 N
b1001001 L
1K
1<
#1620000
0!
0@
#1630000
1!
1@
0K
b1100101110000 M
b1110 N
b1001010 L
1K
0<
1;
#1640000
0!
0@
#1650000
1!
1@
0K
b1100111001000 M
b1111 N
b1001011 L
1K
1<
#1660000
0!
0@
#1670000
1!
1@
0K
b1101000100000 M
b10000 N
b1001100 L
1K
0<
0;
1:
#1680000
0!
0@
#1690000
1!
1@
0K
b1101001111000 M
b10001 N
b1001101 L
1K
1<
#1700000
0!
0@
#1710000
1!
1@
0K
b1101011010000 M
b10010 N
b1001110 L
1K
0<
1;
#1720000
0!
0@
#1730000
1!
1@
0K
b1101100101000 M
b10011 N
b1001111 L
1K
1<
#1740000
0!
0@
#1750000
1!
1@
0K
b1101110000000 M
b0 N
b100 O
b1010000 L
1K
0<
0;
0:
09
18
#1760000
0!
0@
#1770000
1!
1@
0K
b1101111011000 M
b1 N
b1010001 L
1K
1<
#1780000
0!
0@
#1790000
1!
1@
0K
b1110000110000 M
b10 N
b1010010 L
1K
0<
1;
#1800000
0!
0@
#1810000
1!
1@
0K
b1110010001000 M
b11 N
b1010011 L
1K
1<
#1820000
0!
0@
#1830000
1!
1@
0K
b1110011100000 M
b100 N
b1010100 L
1K
0<
0;
1:
#1840000
0!
0@
#1850000
1!
1@
0K
b1110100111000 M
b101 N
b1010101 L
1K
1<
#1860000
0!
0@
#1870000
1!
1@
0K
b1110110010000 M
b110 N
b1010110 L
1K
0<
1;
#1880000
0!
0@
#1890000
1!
1@
0K
b1110111101000 M
b111 N
b1010111 L
1K
1<
#1900000
0!
0@
#1910000
1!
1@
0K
b1111001000000 M
b1000 N
b1011000 L
1K
0<
0;
0:
19
#1920000
0!
0@
#1930000
1!
1@
0K
b1111010011000 M
b1001 N
b1011001 L
1K
1<
#1940000
0!
0@
#1950000
1!
1@
0K
b1111011110000 M
b1010 N
b1011010 L
1K
0<
1;
#1960000
0!
0@
#1970000
1!
1@
0K
b1111101001000 M
b1011 N
b1011011 L
1K
1<
#1980000
0!
0@
#1990000
1!
1@
0K
b1111110100000 M
b1100 N
b1011100 L
1K
0<
0;
1:
#2000000
0!
0@
#2010000
1!
1@
0K
b1111111111000 M
b1101 N
b1011101 L
1K
1<
#2020000
0!
0@
#2030000
1!
1@
0K
b10000001010000 M
b1110 N
b1011110 L
1K
0<
1;
#2040000
0!
0@
#2050000
1!
1@
0K
b10000010101000 M
b1111 N
b1011111 L
1K
1<
#2060000
0!
0@
#2070000
1!
1@
0K
b10000100000000 M
b10000 N
b1100000 L
1K
0<
0;
0:
09
08
17
#2080000
0!
0@
#2090000
1!
1@
0K
b10000101011000 M
b10001 N
b1100001 L
1K
1<
#2100000
0!
0@
#2110000
1!
1@
0K
b10000110110000 M
b10010 N
b1100010 L
1K
0<
1;
#2120000
0!
0@
#2130000
1!
1@
0K
b10001000001000 M
b10011 N
b1100011 L
1K
1<
#2140000
0!
0@
#2150000
1!
1@
0K
b10001001100000 M
b0 N
b101 O
b1100100 L
1K
0<
0;
1:
#2160000
0!
0@
#2170000
1!
1@
0K
b10001010111000 M
b1 N
b1100101 L
1K
1<
#2180000
0!
0@
#2190000
1!
1@
0K
b10001100010000 M
b10 N
b1100110 L
1K
0<
1;
#2200000
0!
0@
#2210000
1!
1@
0K
b10001101101000 M
b11 N
b1100111 L
1K
1<
#2220000
0!
0@
#2230000
1!
1@
0K
b10001111000000 M
b100 N
b1101000 L
1K
0<
0;
0:
19
#2240000
0!
0@
#2250000
1!
1@
0K
b10010000011000 M
b101 N
b1101001 L
1K
1<
#2260000
0!
0@
#2270000
1!
1@
0K
b10010001110000 M
b110 N
b1101010 L
1K
0<
1;
#2280000
0!
0@
#2290000
1!
1@
0K
b10010011001000 M
b111 N
b1101011 L
1K
1<
#2300000
0!
0@
#2310000
1!
1@
0K
b10010100100000 M
b1000 N
b1101100 L
1K
0<
0;
1:
#2320000
0!
0@
#2330000
1!
1@
0K
b10010101111000 M
b1001 N
b1101101 L
1K
1<
#2340000
0!
0@
#2350000
1!
1@
0K
b10010111010000 M
b1010 N
b1101110 L
1K
0<
1;
#2360000
0!
0@
#2370000
1!
1@
0K
b10011000101000 M
b1011 N
b1101111 L
1K
1<
#2380000
0!
0@
#2390000
1!
1@
0K
b10011010000000 M
b1100 N
b1110000 L
1K
0<
0;
0:
09
18
#2400000
0!
0@
#2410000
1!
1@
0K
b10011011011000 M
b1101 N
b1110001 L
1K
1<
#2420000
0!
0@
#2430000
1!
1@
0K
b10011100110000 M
b1110 N
b1110010 L
1K
0<
1;
#2440000
0!
0@
#2450000
1!
1@
0K
b10011110001000 M
b1111 N
b1110011 L
1K
1<
#2460000
0!
0@
#2470000
1!
1@
0K
b10011111100000 M
b10000 N
b1110100 L
1K
0<
0;
1:
#2480000
0!
0@
#2490000
1!
1@
0K
b10100000111000 M
b10001 N
b1110101 L
1K
1<
#2500000
0!
0@
#2510000
1!
1@
0K
b10100010010000 M
b10010 N
b1110110 L
1K
0<
1;
#2520000
0!
0@
#2530000
1!
1@
0K
b10100011101000 M
b10011 N
b1110111 L
1K
1<
#2540000
0!
0@
#2550000
1!
1@
0K
b10100101000000 M
b0 N
b110 O
b1111000 L
1K
0<
0;
0:
19
#2560000
0!
0@
#2570000
1!
1@
0K
b10100110011000 M
b1 N
b1111001 L
1K
1<
#2580000
0!
0@
#2590000
1!
1@
0K
b10100111110000 M
b10 N
b1111010 L
1K
0<
1;
#2600000
0!
0@
#2610000
1!
1@
0K
b10101001001000 M
b11 N
b1111011 L
1K
1<
#2620000
0!
0@
#2630000
1!
1@
0K
b10101010100000 M
b100 N
b1111100 L
1K
0<
0;
1:
#2640000
0!
0@
#2650000
1!
1@
0K
b10101011111000 M
b101 N
b1111101 L
1K
1<
#2660000
0!
0@
#2670000
1!
1@
0K
b10101101010000 M
b110 N
b1111110 L
1K
0<
1;
#2680000
0!
0@
#2690000
1!
1@
0K
b10101110101000 M
b111 N
b1111111 L
1K
1<
#2700000
0!
0@
#2710000
1!
1@
0K
b10110000000000 M
b1000 N
b10000000 L
1K
0<
0;
0:
09
08
07
06
15
#2720000
0!
0@
#2730000
1!
1@
0K
b10110001011000 M
b1001 N
b10000001 L
1K
1<
#2740000
0!
0@
#2750000
1!
1@
0K
b10110010110000 M
b1010 N
b10000010 L
1K
0<
1;
#2760000
0!
0@
#2770000
1!
1@
0K
b10110100001000 M
b1011 N
b10000011 L
1K
1<
#2780000
0!
0@
#2790000
1!
1@
0K
b10110101100000 M
b1100 N
b10000100 L
1K
0<
0;
1:
#2800000
0!
0@
#2810000
1!
1@
0K
b10110110111000 M
b1101 N
b10000101 L
1K
1<
#2820000
0!
0@
#2830000
1!
1@
0K
b10111000010000 M
b1110 N
b10000110 L
1K
0<
1;
#2840000
0!
0@
#2850000
1!
1@
0K
b10111001101000 M
b1111 N
b10000111 L
1K
1<
#2860000
0!
0@
#2870000
1!
1@
0K
b10111011000000 M
b10000 N
b10001000 L
1K
0<
0;
0:
19
#2880000
0!
0@
#2890000
1!
1@
0K
b10111100011000 M
b10001 N
b10001001 L
1K
1<
#2900000
0!
0@
#2910000
1!
1@
0K
b10111101110000 M
b10010 N
b10001010 L
1K
0<
1;
#2920000
0!
0@
#2930000
1!
1@
0K
b10111111001000 M
b10011 N
b10001011 L
1K
1<
#2940000
0!
0@
#2950000
1!
1@
0K
b11000000100000 M
b0 N
b111 O
b10001100 L
1K
0<
0;
1:
#2960000
0!
0@
#2970000
1!
1@
0K
b11000001111000 M
b1 N
b10001101 L
1K
1<
#2980000
0!
0@
#2990000
1!
1@
0K
b11000011010000 M
b10 N
b10001110 L
1K
0<
1;
#3000000
0!
0@
#3010000
1!
1@
0K
b11000100101000 M
b11 N
b10001111 L
1K
1<
#3020000
0!
0@
#3030000
1!
1@
0K
b11000110000000 M
b100 N
b10010000 L
1K
0<
0;
0:
09
18
#3040000
0!
0@
#3050000
1!
1@
0K
b11000111011000 M
b101 N
b10010001 L
1K
1<
#3060000
0!
0@
#3070000
1!
1@
0K
b11001000110000 M
b110 N
b10010010 L
1K
0<
1;
#3080000
0!
0@
#3090000
1!
1@
0K
b11001010001000 M
b111 N
b10010011 L
1K
1<
#3100000
0!
0@
#3110000
1!
1@
0K
b11001011100000 M
b1000 N
b10010100 L
1K
0<
0;
1:
#3120000
0!
0@
#3130000
1!
1@
0K
b11001100111000 M
b1001 N
b10010101 L
1K
1<
#3140000
0!
0@
#3150000
1!
1@
0K
b11001110010000 M
b1010 N
b10010110 L
1K
0<
1;
#3160000
0!
0@
#3170000
1!
1@
0K
b11001111101000 M
b1011 N
b10010111 L
1K
1<
#3180000
0!
0@
#3190000
1!
1@
0K
b11010001000000 M
b1100 N
b10011000 L
1K
0<
0;
0:
19
#3200000
0!
0@
#3210000
1!
1@
0K
b11010010011000 M
b1101 N
b10011001 L
1K
1<
#3220000
0!
0@
#3230000
1!
1@
0K
b11010011110000 M
b1110 N
b10011010 L
1K
0<
1;
#3240000
0!
0@
#3250000
1!
1@
0K
b11010101001000 M
b1111 N
b10011011 L
1K
1<
#3260000
0!
0@
#3270000
1!
1@
0K
b11010110100000 M
b10000 N
b10011100 L
1K
0<
0;
1:
#3280000
0!
0@
#3290000
1!
1@
0K
b11010111111000 M
b10001 N
b10011101 L
1K
1<
#3300000
0!
0@
#3310000
1!
1@
0K
b11011001010000 M
b10010 N
b10011110 L
1K
0<
1;
#3320000
0!
0@
#3330000
1!
1@
0K
b11011010101000 M
b10011 N
b10011111 L
1K
1<
#3340000
0!
0@
#3350000
1!
1@
0K
b11011100000000 M
b0 N
b1000 O
b10100000 L
1K
0<
0;
0:
09
08
17
#3360000
0!
0@
#3370000
1!
1@
0K
b11011101011000 M
b1 N
b10100001 L
1K
1<
#3380000
0!
0@
#3390000
1!
1@
0K
b11011110110000 M
b10 N
b10100010 L
1K
0<
1;
#3400000
0!
0@
#3410000
1!
1@
0K
b11100000001000 M
b11 N
b10100011 L
1K
1<
#3420000
0!
0@
#3430000
1!
1@
0K
b11100001100000 M
b100 N
b10100100 L
1K
0<
0;
1:
#3440000
0!
0@
#3450000
1!
1@
0K
b11100010111000 M
b101 N
b10100101 L
1K
1<
#3460000
0!
0@
#3470000
1!
1@
0K
b11100100010000 M
b110 N
b10100110 L
1K
0<
1;
#3480000
0!
0@
#3490000
1!
1@
0K
b11100101101000 M
b111 N
b10100111 L
1K
1<
#3500000
0!
0@
#3510000
1!
1@
0K
b11100111000000 M
b1000 N
b10101000 L
1K
0<
0;
0:
19
#3520000
0!
0@
#3530000
1!
1@
0K
b11101000011000 M
b1001 N
b10101001 L
1K
1<
#3540000
0!
0@
#3550000
1!
1@
0K
b11101001110000 M
b1010 N
b10101010 L
1K
0<
1;
#3560000
0!
0@
#3570000
1!
1@
0K
b11101011001000 M
b1011 N
b10101011 L
1K
1<
#3580000
0!
0@
#3590000
1!
1@
0K
b11101100100000 M
b1100 N
b10101100 L
1K
0<
0;
1:
#3600000
0!
0@
#3610000
1!
1@
0K
b11101101111000 M
b1101 N
b10101101 L
1K
1<
#3620000
0!
0@
#3630000
1!
1@
0K
b11101111010000 M
b1110 N
b10101110 L
1K
0<
1;
#3640000
0!
0@
#3650000
1!
1@
0K
b11110000101000 M
b1111 N
b10101111 L
1K
1<
#3660000
0!
0@
#3670000
1!
1@
0K
b11110010000000 M
b10000 N
b10110000 L
1K
0<
0;
0:
09
18
#3680000
0!
0@
#3690000
1!
1@
0K
b11110011011000 M
b10001 N
b10110001 L
1K
1<
#3700000
0!
0@
#3710000
1!
1@
0K
b11110100110000 M
b10010 N
b10110010 L
1K
0<
1;
#3720000
0!
0@
#3730000
1!
1@
0K
b11110110001000 M
b10011 N
b10110011 L
1K
1<
#3740000
0!
0@
#3750000
1!
1@
0K
b11110111100000 M
b0 N
b1001 O
b10110100 L
1K
0<
0;
1:
#3760000
0!
0@
#3770000
1!
1@
0K
b11111000111000 M
b1 N
b10110101 L
1K
1<
#3780000
0!
0@
#3790000
1!
1@
0K
b11111010010000 M
b10 N
b10110110 L
1K
0<
1;
#3800000
0!
0@
#3810000
1!
1@
0K
b11111011101000 M
b11 N
b10110111 L
1K
1<
#3820000
0!
0@
#3830000
1!
1@
0K
b11111101000000 M
b100 N
b10111000 L
1K
0<
0;
0:
19
#3840000
0!
0@
#3850000
1!
1@
0K
b11111110011000 M
b101 N
b10111001 L
1K
1<
#3860000
0!
0@
#3870000
1!
1@
0K
b11111111110000 M
b110 N
b10111010 L
1K
0<
1;
#3880000
0!
0@
#3890000
1!
1@
0K
b100000001001000 M
b111 N
b10111011 L
1K
1<
#3900000
0!
0@
#3910000
1!
1@
0K
b100000010100000 M
b1000 N
b10111100 L
1K
0<
0;
1:
#3920000
0!
0@
#3930000
1!
1@
0K
b100000011111000 M
b1001 N
b10111101 L
1K
1<
#3940000
0!
0@
#3950000
1!
1@
0K
b100000101010000 M
b1010 N
b10111110 L
1K
0<
1;
#3960000
0!
0@
#3970000
1!
1@
0K
b100000110101000 M
b1011 N
b10111111 L
1K
1<
#3980000
0!
0@
#3990000
1!
1@
0K
b100001000000000 M
b1100 N
b11000000 L
1K
0<
0;
0:
09
08
07
16
#4000000
0!
0@
#4010000
1!
1@
0K
b100001001011000 M
b1101 N
b11000001 L
1K
1<
#4020000
0!
0@
